isavailable/__init__.py
isavailable-0.1.2.dist-info/entry_points.txt
isavailable-0.1.2.dist-info/LICENSE
isavailable-0.1.2.dist-info/WHEEL
isavailable-0.1.2.dist-info/METADATA
isavailable-0.1.2.dist-info/RECORD
