Metadata-Version: 2.1
Name: isavailable
Version: 0.1.2
Summary: Check Python package distribution name availability on PyPI
Home-page: https://github.com/schneiderfelipe/isavailable
License: MIT
Author: Felipe S. S. Schneider
Author-email: schneider.felipe@posgrad.ufsc.br
Requires-Python: >=3.8,<4.0
Classifier: License :: OSI Approved :: MIT License
Classifier: Programming Language :: Python :: 3
Classifier: Programming Language :: Python :: 3.10
Classifier: Programming Language :: Python :: 3.8
Classifier: Programming Language :: Python :: 3.9
Requires-Dist: requests (>=2.26.0,<3.0.0)
Requires-Dist: typer (>=0.4.0,<0.5.0)
Project-URL: Repository, https://github.com/schneiderfelipe/isavailable
